pyliteflux/__init__.py
pyliteflux/core.py
pyliteflux-0.1.2.dist-info/LICENSE
pyliteflux-0.1.2.dist-info/METADATA
pyliteflux-0.1.2.dist-info/WHEEL
pyliteflux-0.1.2.dist-info/RECORD
