Metadata-Version: 2.1
Name: pyliteflux
Version: 0.1.2
Summary: A lightweight Python Web/TCP server framework implemented with pure Python standard library
Home-page: https://github.com/xiwen-haochi/pyliteflux
License: MIT
Keywords: web framework,tcp server,http server,pure python,learning,teaching,standard library
Author: 'fkl'
Author-email: 18654198191@163.com
Requires-Python: >=3.8,<4.0
Classifier: Development Status :: 4 - Beta
Classifier: Intended Audience :: Developers
Classifier: Intended Audience :: Education
Classifier: License :: OSI Approved :: MIT License
Classifier: Operating System :: OS Independent
Classifier: Programming Language :: Python :: 3
Classifier: Programming Language :: Python :: 3.8
Classifier: Programming Language :: Python :: 3.9
Classifier: Programming Language :: Python :: 3.10
Classifier: Programming Language :: Python :: 3.11
Classifier: Programming Language :: Python :: 3.12
Classifier: Programming Language :: Python :: 3.13
Classifier: Topic :: Education
Classifier: Topic :: Internet :: WWW/HTTP :: HTTP Servers
Classifier: Topic :: Software Development :: Libraries :: Python Modules
Project-URL: Repository, https://github.com/xiwen-haochi/pyliteflux
